keystone_postgres/__about__.py
keystone_postgres/__init__.py
keystone_postgres/concurrency_service.py
keystone_postgres/model_validators.py
keystone_postgres/models.py
keystone_postgres/postgres_service.py
keystone_postgres/postgres_settings.py
keystone_postgres-0.0.1a0.dist-info/METADATA
keystone_postgres-0.0.1a0.dist-info/WHEEL
keystone_postgres-0.0.1a0.dist-info/licenses/LICENSE.txt
keystone_postgres-0.0.1a0.dist-info/RECORD
